vpnctl/__init__.py
vpnctl-0.0.1.dist-info/entry_points.txt
vpnctl-0.0.1.dist-info/LICENSE
vpnctl-0.0.1.dist-info/WHEEL
vpnctl-0.0.1.dist-info/METADATA
vpnctl-0.0.1.dist-info/RECORD
